{"path":".obsidian/plugins/text-extractor/cache/ds/digestive-system-ds-w6-ds-l15-intestines-of-the-dog-and-cat-ds-l15-outline-pdf-d0780772449c8bbb8ffa4b33811d26c5.json","text":"Veterinary Bioscience: Digestive System L E C T U R E 1 5 I N T E S T I N E S O F T H E D O G A N D C A T L E C T U R E R D R N I C H O L A S B A M F O R D n.bamford@unimelb.edu.au I N T E N D E D L E A R N I N G O U T C O M E S At the end of this lecture, you should be able to: - Describe the gross anatomy of the small and large intestines of the dog and cat, including their course and position in the body and relationships to other organs. - Describe the gross anatomy of the anal canal and the clinical importance of the anal sacs. - Describe the gross anatomy of the pancreas of the dog and cat. K E Y W O R D S Intestines; duodenum; jejunum; ileum; caecum; colon; rectum; anus; anal sphincter; anal sacs; mesenteric arteries. L E C T U R E O V E R V I E W This lecture will examine the gross anatomy of the small and large intestines of the dog and cat. The different segments that will be discussed include the duodenum, jejunum, ileum, caecum, colon and rectum. Their course and position within the abdominal cavity and relationships to other organs, as well as their vascular and nervous supply will be outlined. The clinical importance of the anal sacs in these species will be discussed. F U R T H E R R E A D I N G Singh: Dyce, Sack & Wensing’s Textbook of Veterinary Anatomy, 5th Ed. Elsevier, 2018. Boyd: Color Atlas of Clinical Anatomy of the Dog and Cat, 2nd Ed. Mosby, 2001. Hermanson & de Lahunta: Miller and Evans’ Anatomy of the Dog, 5th Ed. Elsevier, 2020. Smallwood: A Guided Tour of Veterinary Anatomy, Saunders, 1992.","libVersion":"0.0.0","langs":"","hash":"","size":0}